{
   "model_config": {
      "model_name": "roberta-base",
      "model_type": "base",
      "downstream_task": "wsc",
      "head_size": 3,
      "epochs": 20,
      "batch_size": 24,
      "lr": 2e-06,
      "num_warmup_steps": 40,
      "seed": 42
   },
   "evaluations": {
      "seat": {
         "6": {
            "effect_size": 0.0837,
            "p_val": 0.3221
         },
         "7": {
            "effect_size": -0.0537,
            "p_val": 0.6219
         },
         "8": {
            "effect_size": 0.064,
            "p_val": 0.371
         },
         "stereo": {
            "effect_size": -0.0659,
            "p_val": 0.7095
         }
      },
      "lpbs": {
         "adjectives": {
            "bias_score": 1.1399,
            "bias_score_std": 0.8944
         },
         "kaneko_stereotypes": {
            "bias_score": 1.2411,
            "bias_score_std": 0.9203
         },
         "occupations": {
            "bias_score": 1.0835,
            "bias_score_std": 0.8543
         }
      },
      "wsc": 54.66
   }
}